foxglove/__init__.py
foxglove/addons.txt
foxglove/prefs.js
foxglove-0.1.10.dist-info/METADATA
foxglove-0.1.10.dist-info/WHEEL
foxglove-0.1.10.dist-info/entry_points.txt
foxglove-0.1.10.dist-info/top_level.txt
foxglove-0.1.10.dist-info/RECORD
