Metadata-Version: 2.1
Name: foxglove
Version: 0.1.10
Summary: Firefox proxy profile manager
Home-page: https://github.com/adamreiser/foxglove
Author: Adam Reiser
Author-email: reiser@defensivecomputing.io
License: MIT
Keywords: mozilla
Platform: UNKNOWN
Classifier: Development Status :: 3 - Alpha
Classifier: Intended Audience :: Developers
Classifier: License :: OSI Approved :: MIT License
Classifier: Programming Language :: Python :: 3
Requires-Dist: mozprofile (>=1.0.0)
Requires-Dist: requests
